Workbook

Sheet Enriched Data
A1: ACCOUNTNUM | B1: Top Group | C1: NAME | D1: VENDOR GROUP | E1: Address | F1: CURRENCY | G1: SUM_AMOUNT | H1: Generalized Category | I1: Category | J1: Additional Services
A2: 113081 | B2: 80% Spend | C2: Morgan Stanley | D2: TRAD | E2: 1 New York Plz;41st floor;New York NY 10004-1901;USA | F2: USD | G2: 1.7243952e+08 | H2: Financial & Accounting Services | I2: Investment Banking & Financial Services | J2: Wealth Management, Investment Banking, Trading, Research, Asset Management
A3: 141936 | B3: 80% Spend | C3: Tombras | D3: MARKETING | E3: PO Box 896838;Charlotte NC 28289;USA | F3: USD | G3: 63836895 | H3: Marketing & Advertising | I3: Full-Service Advertising Agency | J3: Brand Strategy, Media Planning, Digital Marketing, Creative Services, Data Analytics, Social Media
A4: 102840 | B4: 80% Spend | C4: Blackhawk Transport Inc | D4: FRGT | E4: PO Box 667;Racine WI 53401-0667;USA | F4: USD | G4: 30035306 | H4: Freight & Transportation | I4: Freight & Transportation | J4: Trucking, Logistics, Freight Services
A5: 100222 | B5: 80% Spend | C5: Xn Financial -us | D5: INSURANCE | E5: USA | F5: USD | G5: 27778217 | H5: Financial & Accounting Services | I5: Insurance & Financial Services | J5: Insurance Services, Financial Products, Risk Management
A6: 105511 | B6: 80% Spend | C6: Ryder Transportation Services-CHIC | D6: TRAD | E6: PO Box 96723;Chicago IL 60693 6723;USA | F6: USD | G6: 23877181 | H6: Fleet, Vehicle & Auto Services | I6: Truck Leasing & Fleet Management | J6: Truck Leasing, Fleet Maintenance, Dedicated Transportation, Used Truck Sales
A7: 101168 | B7: 80% Spend | C7: C R England Inc | D7: FRGT | E7: PO Box 952407;Saint Louis MO 63195 2407;USA | F7: USD | G7: 22269849 | H7: Fleet, Vehicle & Auto Services | I7: Freight & Trucking Services | J7: Refrigerated Transport, Truckload Shipping, Logistics
A8: 128810 | B8: 80% Spend | C8: Schneider National Carriers, Inc. | D8: FRGT | E8: PO Box 2545;Green Bay WI 54306-2545;USA | F8: USD | G8: 20887754 | H8: Fleet, Vehicle & Auto Services | I8: Truckload & Logistics Services | J8: Truckload, Intermodal, Logistics, Dedicated Trucking, Freight Brokerage, Supply Chain
A9: 103141 | B9: 80% Spend | C9: Averitt Express | D9: FRGT | E9: PO Box 102197;Atlanta GA 30368 2197;USA | F9: USD | G9: 19620030 | H9: Fleet, Vehicle & Auto Services | I9: LTL & Truckload Freight | J9: Less-Than-Truckload Shipping, Full Truckload, Expedited Freight, Supply Chain Solutions
A10: 147062 | B10: 80% Spend | C10: USA Truck LLC | D10: FRGT | E10: 3200 INDUSTRIAL PARK RD;VAN BUREN AR 72956-6110;USA | F10: USD | G10: 19166697 | H10: Freight & Transportation | I10: Freight & Transportation | J10: Truckload, Dedicated, Intermodal, Logistics, Brokerage, Freight Services
A11: 131589 | B11: 80% Spend | C11: Concentrix Solutions Corporation | D11: TRAD | E11: 44111 Nobel Dr;Fremont CA 94538-3173;USA | F11: USD | G11: 15925508 | H11: General Services | I11: Business Process Outsourcing (BPO) | J11: Customer Experience, Technical Support, Digital Engineering, AI Solutions
A12: 103271 | B12: 80% Spend | C12: NFI | D12: FRGT | E12: PO Box 417727;Boston MA 02241-7727;USA | F12: USD | G12: 15576392 | H12: Freight & Transportation | I12: Third-Party Logistics (3PL) | J12: Warehousing, Transportation, Dedicated Fleet, Supply Chain Solutions, Drayage
A13: 147102 | B13: 80% Spend | C13: WEX Bank | D13: TRAD | E13: PO Box 6293;Carol Stream IL 60197;USA | F13: USD | G13: 15479315 | H13: General Services | I13: Fleet Payment Solutions | J13: Fleet Cards, Fuel Cards, Payment Processing, Expense Management, Corporate Payments
... A37: 131406 | B37: 80% Spend | C37: Legacy Support Services | D37: TRAD | E37: 601 Texas Central Parkway;Waco TX 76712;USA | F37: USD | G37: 3530311.6 | H37: Consulting & Professional Services | I37: Payroll & HR Services | J37: Technical Support, Help Desk, IT Infrastructure, Network Management
A38: 000526 | B38: 80% Spend | C38: Ryder Truck Rental Canada | D38: TRAD | E38: PO BOX 9464 STN A;TORONTO ON M5W 4E1;CAN | F38: CAD | G38: 3293556.4 | H38: Fleet, Vehicle & Auto Services | I38: Truck Rental Services | J38: Truck Rental, Commercial Vehicles, Fleet Solutions
A39: 147475 | B39: 80% Spend | C39: Concept Logistics | D39: FRGT | E39: 701 Seneca St ;Suite 140F;Buffalo NY 14210;USA | F39: USD | G39: 3261841 | H39: Freight & Transportation | I39: Freight Brokerage & Logistics | J39: LTL Shipping, Truckload, Intermodal, Supply Chain Management
A40: 125966 | B40: 80% Spend | C40: Los Angeles County Employees Retirement | D40: RENT | E40: 300 N LAKE AVE;Ste. 850;PASADENA CA 91101-4109;USA | F40: USD | G40: 3020990 | H40: Rent Space | I40: Public Employee Retirement System | J40: Pension Administration, Retirement Benefits, Investment Management
A41: 101238 | B41: 80% Spend | C41: Pacab LLC | D41: RENT | E41: LOCKBOX #15693;15693 COLLECTIONS CENTER DR;Chicago IL 60693;USA | F41: USD | G41: 2943600.5 | H41: Rent Space | I41: Commercial Property Lease | J41: Real Estate, Property Management
A42: 103294 | B42: 80% Spend | C42: HYG Financial Services, Inc. | D42: TRAD | E42: PO Box 77102;Minneapolis MN 55480;USA | F42: USD | G42: 2915710.6 | H42: Fleet, Vehicle & Auto Services | I42: Lift Truck Financing | J42: Forklift Leasing, Equipment Loans, Fleet Financing, Asset Remarketing
A43: 130400 | B43: 80% Spend | C43: BTC II Holdco, LLC | D43: RENT | E43: 900 WILSHIRE BLVD;STE 2400;LOS ANGELES CA 90017-4701;USA | F43: USD | G43: 2900407.4 | H43: Rent Space | I43: Commercial Property Lease | J43: Real Estate Investment, Property Management
A44: 120598 | B44: 80% Spend | C44: Boyle at 54th, LLC | D44: RENT | E44: 3010 Old Ranch Pkwy;Suite 470;Seal Beach CA 90740-2764;USA | F44: USD | G44: 2860899.1 | H44: Rent Space | I44: Commercial Property Lease | J44: Real Estate, Property Management
A45: 128100 | B45: 80% Spend | C45: Gateway Logistics, Inc. | D45: FRGT | E45: 4250 Creek Rd;Cincinnati OH 45241-2956;USA | F45: USD | G45: 2749533 | H45: Freight & Transportation | I45: Freight & Logistics | J45: Trucking, Supply Chain, Warehousing, Freight Brokerage
A46: 141947 | B46: 80% Spend | C46: Terreno Realty Corporation | D46: RENT | E46: 101 MONTGOMERY ST;STE 200;SAN FRANCISCO CA 94104-4151;USA | F46: USD | G46: 2732693.1 | H46: Rent Space | I46: Industrial Real Estate Investment (REIT) | J46: Industrial Property, Warehouse, Distribution, Logistics Real Estate, Net Lease
A47: 144898 | B47: 80% Spend | C47: Gateway Pacific Vista LLC | D47: RENT | E47: PO Box 209233;Austin TX 78720;USA | F47: USD | G47: 2711818.2 | H47: Rent Space | I47: Commercial Property Lease | J47: Real Estate, Property Management
A48: 143344 | B48: 80% Spend | C48: Prologis, L.P | D48: RENT | E48: 1800 Wazee Street;Suite 500;Denver CO 80202;USA | F48: USD | G48: 2678231.5 | H48: Rent Space | I48: Industrial Real Estate Investment | J48: Industrial Real Estate, Warehouse, Distribution, REIT Operations
A49: 129672 | B49: 80% Spend | C49: Dyer Business Park c/o Shea Ctr Cor | D49: RENT | E49: 130 Vantis Dr;Ste 200;Aliso Viejo CA 92656-2691;USA | F49: USD | G49: 2634362.5 | H49: Rent Space | I49: Commercial Property Lease | J49: Real Estate, Business Park, Property Management
A50: 100035 | B50: 80% Spend | C50: FKQ Marketing | D50: MARKETING | E50: 15351 Roosevelt Blvd;Clearwater FL 33760 3534;USA | F50: USD | G50: 2602682 | H50: Marketing & Advertising | I50: Full-Service Advertising Agency | J50: Advertising, Branding, Media Planning, Digital Marketing, Creative Services
... A86: 142206 | B86: 80% Spend | C86: 94 Business Park Drive Associates | D86: RENT | E86: c/o Mandlebaum & Mandlebaum;354 Eisenhower Parkway;Suite 1900;Livingston NJ 07039;USA | F86: USD | G86: 1432760.6 | H86: Rent Space | I86: Commercial Property Lease | J86: Industrial Real Estate, Business Park Space
A87: 000558 | B87: 80% Spend | C87: Orlando Corporation | D87: RENT | E87: 6205-B Airport Rd 5th Floor;Mississauga ON L4V 1E3;CAN | F87: CAD | G87: 1420725.2 | H87: Rent Space | I87: Commercial Property Lease | J87: Industrial Real Estate, Office Space, Property Development
A88: 146218 | B88: 80% Spend | C88: E Thomas Harvey III | D88: RENT | E88: 405 E Marsh Lane;Suite 1;Newport DE 19804;USA | F88: USD | G88: 1411964.1 | H88: Rent Space | I88: Commercial Property Lease | J88: Real Estate, Property Management
A89: 140041 | B89: 80% Spend | C89: BA One REIT LLC | D89: RENT | E89: 101 W ELM ST;Suite 600;CONSHOHOCKEN PA 19428-2075;USA | F89: USD | G89: 1404197.7 | H89: Rent Space | I89: Commercial Property Lease | J89: Real Estate Investment, Property Management
A90: 113911 | B90: 80% Spend | C90: Sullivan & Cromwell LLP | D90: LEGAL | E90: Attn: Treaury Dept/Rm 2021;125 Broad Street;New York NY 10004;USA | F90: USD | G90: 1371035.3 | H90: Legal Services | I90: Full-Service Law Firm | J90: M&A, Capital Markets, Securities, Litigation, Financial Restructuring, Tax, IP, Real Estate
A91: 150422 | B91: 80% Spend | C91: Wheels Leasing Canada LTD | D91: TRAD | E91: 6733 Mississauga Rd, Suite 310 ;Mississauga ON L5N 6J5;CAN | F91: CAD | G91: 1348072.5 | H91: Fleet, Vehicle & Auto Services | I91: Fleet Leasing & Management | J91: Fleet Leasing, Fleet Management, Driver Solutions, Vehicle Remarketing, Fleet Analytics
A92: 150283 | B92: 80% Spend | C92: Simon Kucher & Partners | D92: TRAD | E92: 201 Washington St,;One Boston Pl, Suite 3301;BOSTON MA 02108-4407;USA | F92: USD | G92: 1343918.9 | H92: Consulting & Professional Services | I92: Pricing & Growth Strategy Consulting | J92: Revenue Growth, Commercial Strategy, Pricing Optimization, M&A Advisory, Market Entry Strategy
A93: 106343 | B93: 80% Spend | C93: GFI Big Joe LLC | D93: RENT | E93: PO Box 75917;Baltimore MD 21275-5917;USA | F93: USD | G93: 1302281.4 | H93: Rent Space | I93: Commercial Property Lease | J93: Real Estate, Property Management
A94: 144855 | B94: 80% Spend | C94: Standard Ins Co (Life/Disability) | D94: TRAD | E94: PO Box 3789;Portland OR 97208;USA | F94: USD | G94: 1286415.7 | H94: Insurance & Risk Management | I94: Group Insurance & Employee Benefits | J94: Life Insurance, Disability Insurance, Dental, Vision, Retirement Plans, Absence Management
A95: 130035 | B95: 80% Spend | C95: GuidePoint Security Holdings LLC | D95: TRAD | E95: 1900 RESTON METRO PLZ; Suite 701;RESTON VA 20190-5218;USA | F95: USD | G95: 1267723.1 | H95: Consulting & Professional Services | I95: Cybersecurity Consulting & Solutions | J95: Cloud Security, Identity & Access Management, Endpoint Security, Incident Response, Network Security, Managed Security
A96: 118550 | B96: 80% Spend | C96: LMO Creekside Dist., LLC | D96: RENT | E96: 687 Old Willets Path;Suite C;Hauppauge NY 11788-4118;USA | F96: USD | G96: 1266405.8 | H96: Rent Space | I96: Commercial Property Lease | J96: Industrial Real Estate, Distribution Facilities
A97: 150449 | B97: 80% Spend | C97: Aetna Life Insurance Company Medical | D97: BENEFITS | E97: 151 FARMINGTON AVE;HARTFORD CT 06156-0001;USA | F97: USD | G97: 1255419.2 | H97: Insurance & Risk Management | I97: Health Insurance & Benefits | J97: Medical Plans, Dental, Vision, Wellness Programs
A98: 123744 | B98: 80% Spend | C98: Mode Transportation, LLC | D98: FRGT | E98: PO Box 654371;Dallas TX 75265;USA | F98: USD | G98: 1250507.5 | H98: Freight & Transportation | I98: Freight Brokerage & Logistics | J98: LTL, Truckload, Intermodal, Temperature-Controlled, Supply Chain Solutions
A99: 142551 | B99: 80% Spend | C99: HDC Properties Hanua Logistic Ctr | D99: RENT | E99: 1250 Kapiolani Blvd.;Honolulu HI 96814;USA | F99: USD | G99: 1240916.1 | H99: Rent Space | I99: Commercial Property Lease | J99: Industrial Real Estate, Logistics Facilities, Warehouse Space
... A107: 109756 | B107: 80% Spend | C107: Jing Jiang Asian-Pacific Special Mt | D107: TRAD | E107: No. 19 Cheng Xi Ave;Jingjiang City;Jiangsu Province;Peoples Republic of China 214500;USA | F107: USD | G107: 1143309 | H107: General Services | I107: Specialty Metal Manufacturing | J107: Precision Metal Parts, Forging, Machining, Industrial Components
A108: 000936 | B108: 80% Spend | C108: CREIT Management LP in Trust for CREIT Alberta Industrial | D108: RENT | E108: 1030, 355-4th Avenue SW Calgary Place;Calgary AB T2P 0J1;CAN | F108: CAD | G108: 1130141.9 | H108: Rent Space | I108: Commercial Property Lease | J108: Real Estate, Property Management
A109: 125754 | B109: 80% Spend | C109: 625 Universtiy Leasehold Owner, LLC | D109: RENT | E109: C/O WS Development Assoc.;33 Boylston ST. Ste. 3000;Chestnut Hill MA 02467;USA | F109: USD | G109: 1123635.9 | H109: Rent Space | I109: Commercial Property Lease | J109: Retail Real Estate, Mixed-Use Development, Property Management
A110: 144981 | B110: 80% Spend | C110: Pac West Equities dba PW Fund Do not use - use 152202 | D110: RENT | E110: 555 Capitol Mall;Suite 900;Sacramento CA 95814;USA | F110: USD | G110: 1121824.6 | H110: Rent Space | I110: Commercial Property Lease | J110: Real Estate Investment, Property Management
A111: 132018 | B111: 80% Spend | C111: UKG Inc. | D111: TRAD | E111: PO Box 930953;Atlanta GA 31193-0953;USA | F111: USD | G111: 1120512.4 | H111: Technology & Software | I111: Workforce Management / HCM Platform | J111: Payroll, HR, Talent Management, Workforce Analytics, Time & Attendance, Benefits Admin
A112: 131381 | B112: 80% Spend | C112: 29899 SW Boones Ferry Rd Co LLC | D112: RENT | E112: PO Box 743130;Los Angeles CA 90074-3130;USA | F112: USD | G112: 1119426.2 | H112: Rent Space | I112: Commercial Property Lease | J112: Real Estate, Property Management
A113: 147720 | B113: 80% Spend | C113: Rastegar Rel Fund Mgt Infinity Park | D113: RENT | E113: 11044 Research Blvd;Ste D-110;Austin TX 78759;USA | F113: USD | G113: 1110450 | H113: Rent Space | I113: Commercial Property Lease | J113: Real Estate Investment, Property Management
A114: 102720 | B114: 80% Spend | C114: Werner Enterprises Inc | D114: FRGT | E114: 14507 Frontier Rd;Omaha NE 68138-3808;USA | F114: USD | G114: 1105487.4 | H114: Freight & Transportation | I114: Freight & Transportation | J114: Truckload, Dedicated, Intermodal, Logistics, Freight Management, Fleet Services
A115: 129788 | B115: 80% Spend | C115: Pine Forest Everett, LLC | D115: RENT | E115: 11980 NE 24th St;Suite 200;Bellevue WA 98005-1516;USA | F115: USD | G115: 1105480 | H115: Rent Space | I115: Commercial Property Lease | J115: Real Estate, Property Management
A116: 132155 | B116: 80% Spend | C116: Focused Labs, Inc. | D116: TRAD | E116: 433 W Van Buren St;STE 1100-B;Chicago IL 60607;USA | F116: USD | G116: 1101351.1 | H116: Consulting & Professional Services | I116: Custom Software Development & AI Consulting | J116: AI Agent Development, Cloud Migration, Platform Deployment, LangChain, Software Consulting
A117: 123317 | B117: 80% Spend | C117: One Fifteen-M-Woodridge, L.L.C. | D117: RENT | E117: 205 Mill Rd;Edison NJ 08837-3801;USA | F117: USD | G117: 1096016.6 | H117: Rent Space | I117: Commercial Property Lease | J117: Real Estate, Property Management
A118: 150149 | B118: 80% Spend | C118: JM Holdings USA LLC | D118: RENT | E118: 1600 S Airport Dr Ste 100;Mc Kinney TX 75069;USA | F118: USD | G118: 1092959.5 | H118: Rent Space | I118: Commercial Property Lease | J118: Real Estate, Property Management
A119: 104039 | B119: 80% Spend | C119: AAFES | D119: TRAD | E119: Attn: Tiffany Thompson;FA-C-AR/CONCESSION UNIT;3911 S WALTON WALKER BLVD;Dallas TX 75236-1598;USA | F119: USD | G119: 1080799.1 | H119: Government & Military | I119: Military Retail Services | J119: Tax-Free Shopping, E-Commerce, Military Family Support
A120: 140845 | B120: 80% Spend | C120: Almar Management LLC | D120: RENT | E120: 730 Arcady Rd;Santa Barbara CA 93108;USA | F120: USD | G120: 1058175.9 | H120: Rent Space | I120: Commercial Property Lease | J120: Real Estate, Property Management
... A132: 113592 | B132: 20% Spend | C132: McClellan Park LLC | D132: RENT | E132: 3140 Peacekeeper Way;McClellan CA 95652-2508;USA | F132: USD | G132: 940083.42 | H132: Rent Space | I132: Commercial Property Lease | J132: Business Park, Industrial Real Estate, Property Management
A133: 000847 | B133: 20% Spend | C133: Portable Storage Canada, LTD | D133: TRAD | E133: CAN | F133: CAD | G133: 922489.08 | H133: Rent Space | I133: Portable Storage Services | J133: Container Rental, Moving Storage, On-Site Storage
A134: 145411 | B134: 20% Spend | C134: PROS Inc. | D134: TRAD | E134: 3200 Kirby Drive;Suite 600;Houston TX 77098;USA | F134: USD | G134: 919265.91 | H134: Technology & Software | I134: AI-Powered Price Optimization | J134: Revenue Management, Dynamic Pricing, Sales Effectiveness, CPQ, eCommerce
A135: 147416 | B135: 20% Spend | C135: Logik.io Inc | D135: TRAD | E135: 570 Lake Cook Rd ;Suite 406;Deerfield IL 60015;USA | F135: USD | G135: 919135.89 | H135: Technology & Software | I135: CPQ & Commerce Configuration Platform | J135: Product Configuration, Guided Selling, Commerce Engines, Quote Automation
A136: 103229 | B136: 20% Spend | C136: CB Luna Industrial No 2 | D136: RENT | E136: 1722 Routh Street Ste 770;Dallas TX 75201-2535;USA | F136: USD | G136: 903325.94 | H136: Rent Space | I136: Commercial Property Lease | J136: Real Estate, Property Management
A137: 108895 | B137: 20% Spend | C137: RCCI Inc | D137: RENT | E137: Cushman & Wakefield of CA Dept #tx6260;Rcci Inc. PO Box 511335;Los Angeles CA 90051;USA | F137: USD | G137: 898733.1 | H137: Rent Space | I137: Commercial Real Estate Services | J137: Property Management, Facility Services, Commercial Real Estate
A138: 118662 | B138: 20% Spend | C138: ARA-B, LLC | D138: RENT | E138: 1505 S Redwood Rd;Salt Lake City UT 84104-5106;USA | F138: USD | G138: 893729.56 | H138: Rent Space | I138: Commercial Property Lease | J138: Real Estate, Property Management
A139: 131582 | B139: 20% Spend | C139: Amazon Capital Services, Inc. | D139: TRAD | E139: po box 035184;Seattle WA 98124;USA | F139: USD | G139: 871716.32 | H139: General Services | I139: Business Procurement Platform | J139: Office Supplies, IT Equipment, Breakroom Supplies, Janitorial Supplies
A140: 107576 | B140: 20% Spend | C140: Ashley Romulus LLC | D140: RENT | E140: 9810 S Dorchester Ave;Chicago IL 60628 1727;USA | F140: USD | G140: 870522.44 | H140: Rent Space | I140: Commercial Property Lease | J140: Real Estate, Property Management
A141: 113877 | B141: 20% Spend | C141: Manassas Logistics Center LLC | D141: RENT | E141: 1717 McKinney Ave;STE 1900;Dallas TX 75202;USA | F141: USD | G141: 864379.67 | H141: Rent Space | I141: Commercial Property Lease | J141: Industrial Real Estate, Logistics Facilities, Warehouse Space
A142: 126593 | B142: 20% Spend | C142: MTA Distributors LLC | D142: TRAD | E142: MSC 7573;PO Box 415000;Nashville TN 37241;USA | F142: USD | G142: 862739.67 | H142: HVAC, Plumbing & Mechanical | I142: HVAC Parts & Equipment Distribution | J142: HVAC Supplies, Refrigeration Parts, Equipment Wholesale
A143: 103418 | B143: 20% Spend | C143: Cascades West LLC | D143: RENT | E143: C/O ONLINE DISTRIBUTING;14093 BALBOA BLVD UNIT A;Sylmar CA 91342;USA | F143: USD | G143: 862555.84 | H143: Rent Misc | I143: Individual Contractor/Consultant | J143: Professional Services
A144: 141739 | B144: 20% Spend | C144: The Westwood Companies Inc | D144: RENT | E144: 687 Old Willets Path;Suite C;Hauppauge NY 11788;USA | F144: USD | G144: 860922.03 | H144: Rent Space | I144: Commercial Property Lease | J144: Real Estate, Property Management, Commercial Leasing
A145: 147153 | B145: 20% Spend | C145: IL Trep Kingsland, LLC | D145: RENT | E145: 3657 Briarpark Drive;Ste 300;Houston TX 77042;USA | F145: USD | G145: 858347.43 | H145: Rent Space | I145: Commercial Property Lease | J145: Real Estate, Property Management, Commercial Leasing
... A162: 142693 | B162: 20% Spend | C162: SL Project Texas 2, LP | D162: RENT | E162: 3200 Gracie Kitz Lane;Suite 500;Austin TX 78758;USA | F162: USD | G162: 756920.93 | H162: Rent Space | I162: Commercial Property Lease | J162: Real Estate, Property Management
A163: 000640 | B163: 20% Spend | C163: Wesgroup Properties Ltd. | D163: RENT | E163: 2000 – 595 Burrard Street;Vancouver BC V6C 0E4;CAN | F163: CAD | G163: 754877.15 | H163: Rent Space | I163: Commercial Real Estate Development | J163: Commercial Real Estate, Industrial, Retail, Mixed-Use Development, Property Management
A164: 001348 | B164: 20% Spend | C164: Cosa Nova Fashions | D164: RENT | E164: 50 Dufflaw Rd;Toronto ON M6A 2W1;CAN | F164: CAD | G164: 751421.85 | H164: Rent Space | I164: Commercial Property Lease | J164: Retail Real Estate, Fashion Retail Space
A165: 115419 | B165: 20% Spend | C165: Mastech Digital Technologies Inc. | D165: TRAD | E165: PO Box 642915;Pittsburgh PA 15264-2915;USA | F165: USD | G165: 749398 | H165: HR, Staffing & Employee Services | I165: IT Staffing & Digital Transformation | J165: IT Staff Augmentation, Data Analytics, Cloud Services, AI/ML, Digital Learning
A166: 125166 | B166: 20% Spend | C166: Aetna Life Insurance Company Voluntary | D166: BENEFITS | E166: 151 Farmington Ave;Hartford CT 06156;USA | F166: USD | G166: 743813.29 | H166: Insurance & Risk Management | I166: Voluntary Employee Benefits | J166: Life Insurance, Disability, Supplemental Coverage
A167: 127357 | B167: 20% Spend | C167: RSM US LLP | D167: TRAD | E167: 5155 Paysphere Circle;Chicago IL 60674;USA | F167: USD | G167: 742260.38 | H167: Financial & Accounting Services | I167: Audit, Tax & Consulting (Top 10 Accounting) | J167: Audit & Assurance, Tax Advisory, Management Consulting, Risk Advisory, Financial Advisory, Technology Consulting
A168: 132077 | B168: 20% Spend | C168: Avot Realty Sanford Logistics Ctr | D168: RENT | E168: 17304 Preston Rd ;Suite 550;Dallas TX 75252;USA | F168: USD | G168: 741625.92 | H168: Rent Space | I168: Commercial Property Lease | J168: Industrial Real Estate, Logistics Center
A169: 132293 | B169: 20% Spend | C169: San Marcos Warehouse LLC | D169: RENT | E169: 280 Daines St;Ste 300;Birmingham MI 48009-6243;USA | F169: USD | G169: 736646.23 | H169: Rent Space | I169: Commercial Property Lease | J169: Real Estate, Property Management
A170: 105934 | B170: 20% Spend | C170: AmeriGas -371473 | D170: UTIL | E170: PO Box 371473;Pittsburgh PA 15250-7473;USA | F170: USD | G170: 731030.66 | H170: Freight & Transportation | I170: Propane Delivery Services | J170: Tank Installation, Propane Delivery, Grill Tank Exchange, Commercial & Residential
A171: 142157 | B171: 20% Spend | C171: TCD245 Sunbelt Property LLC-Do Not Use | D171: RENT | E171: 600 Northlake Drive;Suite 130;Altamonte Springs FL 32701;USA | F171: USD | G171: 727990.13 | H171: Rent Space | I171: Commercial Property Lease | J171: Real Estate, Property Management
A172: 120299 | B172: 20% Spend | C172: Marlboro Dist Rte 9 LLC | D172: RENT | E172: 687 Old Willets Path;Suite C;Hauppauge NY 11788-4118;USA | F172: USD | G172: 727935.02 | H172: Rent Space | I172: Commercial Property Lease | J172: Real Estate, Property Management
A173: 113342 | B173: 20% Spend | C173: Columbia Georgia Horizon Industrl | D173: RENT | E173: PO Box 848138-66;Dallas TX 75284;USA | F173: USD | G173: 726084.77 | H173: Rent Space | I173: Commercial Property Lease | J173: Industrial Real Estate, Property Management
A174: 123090 | B174: 20% Spend | C174: Warren Warehouse,LLC | D174: RENT | E174: 280 Daines St;Suite 300;Birmingham MI 48009-6243;USA | F174: USD | G174: 722774.2 | H174: Rent Space | I174: Warehouse & Storage Facility | J174: Warehousing, Distribution, Storage, Logistics, Inventory Management
A175: 120381 | B175: 20% Spend | C175: 94-40 Merrick Blvd. LLC- DO NOT USE-USE 111153 | D175: RENT | E175: 9402 150th St;Jamaica NY 11435-4525;USA | F175: USD | G175: 717324.83 | H175: Rent Space | I175: Commercial Property Lease | J175: Real Estate, Property Management
A176: 111430 | B176: 20% Spend | C176: TransForce Inc. | D176: TRAD | E176: PO Box 69250;Baltimore MD 21264-9250;USA | F176: USD | G176: 709450.04 | H176: HR, Staffing & Employee Services | I176: Workforce Solutions & Staffing | J176: Driver Staffing, Temporary Staffing, Logistics, Workforce Management
... A181: 127448 | B181: 20% Spend | C181: CK Ridge Creek West lll, LLC | D181: RENT | E181: 301 S College St;Suite 2800;Charlotte NC 28202-6000;USA | F181: USD | G181: 688317.92 | H181: Rent Space | I181: Commercial Property Lease | J181: Real Estate, Property Management
A182: 001355 | B182: 20% Spend | C182: Stevens Group Management dba L&M Ent. Ltd. | D182: RENT | E182: 20 MacDonald Ave;Dartmouth NS B3B 1C5;CAN | F182: CAD | G182: 682975.51 | H182: Rent Space | I182: Commercial Property Lease | J182: Real Estate, Property Management
A183: 100133 | B183: 20% Spend | C183: Fastenal | D183: TRAD | E183: PO Box 1286;Winona MN 55987 7286;USA | F183: USD | G183: 681424.55 | H183: Industrial Equipment & Supply | I183: Industrial Distribution & Supply | J183: Fasteners, Safety Products, Cutting Tools, Industrial Vending, Custom Manufacturing
A184: 116022 | B184: 20% Spend | C184: Merritt Properties, LLC-Elkridge | D184: RENT | E184: 2066 Lord Baltimore Dr;Windsor Mill MD 21244-2501;USA | F184: USD | G184: 678722.49 | H184: Rent Space | I184: Commercial Property Lease | J184: Industrial Real Estate, Office Space, Property Management
A185: 116096 | B185: 20% Spend | C185: Teleport Logistic Services Inc. | D185: FRGT | E185: 503-7700 Hurontario Street Suite #10;Brampton ON L6Y 4M3;CAN | F185: USD | G185: 676156.76 | H185: Freight & Transportation | I185: Freight Forwarding & Customs Brokerage | J185: International Freight, Customs Brokerage, Warehousing, Cross-Border Shipping, Supply Chain
A186: 131242 | B186: 20% Spend | C186: Clackamas Commons II LLC | D186: RENT | E186: 1101 SE Tech Center Dr;sTE 160;Vancouver WA 98683-5504;USA | F186: USD | G186: 673399.83 | H186: Rent Space | I186: Commercial Property Lease | J186: Real Estate, Property Management
A187: 127440 | B187: 20% Spend | C187: 799A Kahelu Ave, LLC | D187: RENT | E187: 481 Carlisle Dr;Herndon VA 20170-4882;USA | F187: USD | G187: 671370.87 | H187: Rent Space | I187: Commercial Property Lease | J187: Real Estate, Property Management
A188: 131063 | B188: 20% Spend | C188: Carrot HR Inc. dba Assembly | D188: TRAD | E188: 3422 Schooner Ave;#8;Marina del Rey CA 90292-5782;USA | F188: USD | G188: 670458.24 | H188: Construction & Contracting | I188: HVAC & Building Systems | J188: Air Conditioning, Heating, Refrigeration, Building Automation, Fire & Security
A189: 128840 | B189: 20% Spend | C189: Prologis USLV Subreit 4, LLC | D189: RENT | E189: 1800 Wazee St;Ste 500;Denver CO 80202-2526;USA | F189: USD | G189: 667222.65 | H189: Rent Space | I189: Industrial Real Estate Investment | J189: Industrial Real Estate, Warehouse, Distribution, REIT Operations
A190: 128502 | B190: 20% Spend | C190: TDC Charleston Partners I, LLC | D190: RENT | E190: PO Box 22796;Charleston SC 29413;USA | F190: USD | G190: 661718.13 | H190: Rent Space | I190: Commercial Property Lease | J190: Real Estate, Property Management
A191: 147356 | B191: 20% Spend | C191: Guide Kenswick DRE, LLC | D191: RENT | E191: 1700 S MacDill Ave;Suite 220;Tampa FL 33629;USA | F191: USD | G191: 659917 | H191: Rent Space | I191: Commercial Property Lease | J191: Real Estate, Property Management
A192: 109671 | B192: 20% Spend | C192: Franco Transport, Inc. | D192: TRAD | E192: PO Box 2383;Chino Hills CA 91709 0080;USA | F192: USD | G192: 658942.5 | H192: Fleet, Vehicle & Auto Services | I192: Freight & Trucking Services | J192: Trucking, Freight Hauling, LTL & FTL, Transportation
A193: 151548 | B193: 20% Spend | C193: Walker Ford Company Inc | D193: TRAD | E193: 17556 US HIGHWAY 19 N;CLEARWATER FL 33764-3517;USA | F193: USD | G193: 655047.81 | H193: Fleet, Vehicle & Auto Services | I193: Auto Dealership | J193: Ford Vehicles, New & Used Cars, Trucks, Service, Parts, Fleet Sales
A194: 144662 | B194: 20% Spend | C194: West Gate Industrial Park LLC | D194: RENT | E194: PO Box 10066;Eugene OR 97440;USA | F194: USD | G194: 654547.32 | H194: Rent Space | I194: Commercial Property Lease | J194: Real Estate, Industrial Property, Property Management
... A264: 115524 | B264: 20% Spend | C264: J&B Holdings LLC | D264: RENT | E264: 1605 Mound Ave;Jacksonville IL 62650;USA | F264: USD | G264: 476735.71 | H264: Rent Space | I264: Commercial Property Lease | J264: Real Estate, Property Management
A265: 150372 | B265: 20% Spend | C265: Infios US, Inc. | D265: TRAD | E265: Minnesota Center, ;7760 France Avenue.S., Ste. 800;BLOOMINGTON MN 55435;USA | F265: USD | G265: 474889.5 | I265: Supply Chain & Warehouse Management Software | J265: Warehouse Management System, Voice Picking, Slotting Optimization, Multi-Carrier Shipping, Supply Chain Analytics
...

Sheet Sheet1
A1: ACCOUNTNUM | B1: Company Name | C1: VENDOR GROUP | D1: Main Technical Service | E1: Additional Technical Services
A2: 1265 | B2: Moving Waldo, Inc. | C2: TRAD | D2: Relocation Tech Platform | E2: Utility Setup, Change of Address Automation
A3: 110288 | B3: Southeast Industrial Equipment | C3: TRAD | D3: Material Handling Solutions | E3: Fleet Management, Equipment Telematics
A4: 129283 | B4: Five9 Inc. | C4: TRAD | D4: Cloud Contact Center (CCaaS) | E4: AI Virtual Agents, Workforce Engagement
A5: 130479 | B5: RG Group | C5: TRAD | D5: Motion Control & Fluid Power | E5: Robotics, Hydraulic/Pneumatic Systems
A6: 131910 | B6: Tata Consultancy Services | C6: TRAD | D6: IT Services & Managed Solutions | E6: Cloud Migration, Software Development
A7: 132018 | B7: UKG Inc. | C7: TRAD | D7: Workforce Management / HRIS | E7: Payroll, Talent Management, Analytics
A8: 142746 | B8: ListEngage, LLC | C8: TRAD | D8: Salesforce Marketing Cloud | E8: Digital Strategy, CRM Consulting
A9: 143336 | B9: Spectora, Inc. | C9: TRAD | D9: Home Inspection Software | E9: Mobile App, Business Management Tools
A10: 143337 | B10: Paylode, Inc. | C10: TRAD | D10: Customer Perk Management | E10: Embedded Rewards, API Integration
A11: 144944 | B11: Bestpass, Inc. | C11: TRAD | D11: Toll Management Solutions | E11: Fleet Administration, Violation Processing
A12: 145411 | B12: PROS Inc. | C12: TRAD | D12: AI-Powered Price Optimization | E12: Revenue Management, Sales Effectiveness
A13: 145905 | B13: Ankura Consulting Group LLC | C13: TRAD | D13: Data & Technology Consulting | E13: Cybersecurity, Forensic Accounting
A14: 147416 | B14: Logik.io Inc | C14: TRAD | D14: CPQ (Configure, Price, Quote) | E14: Commerce Engines, Product Configuration

Sheet Pivot Table
A1: Top Group | B1: 80% Spend
A3: Row Labels | B3: Vendors | C3: Spend
A4: Rent Space | B4: 47 | C4: 86679822
A5: Freight & Transportation | B5: 21 | C5: 1.1657495e+08
A6: Fleet, Vehicle & Auto Services | B6: 16 | C6: 1.3315125e+08
A7: Consulting & Professional Services | B7: 8 | C7: 20184121
A8: Insurance & Risk Management | B8: 7 | C8: 36325446
A9: Claims Management & TPA | B9: 1 | C9: 3865366.5
A10: Gallagher Bassett Services, Inc. | B10: 1 | C10: 3865366.5
A11: Group Insurance & Employee Benefits | B11: 1 | C11: 1286415.7
A12: Standard Ins Co (Life/Disability) | B12: 1 | C12: 1286415.7
A13: Health Insurance & Benefits | B13: 1 | C13: 1255419.2
A14: Aetna Life Insurance Company Medical | B14: 1 | C14: 1255419.2
A15: Insurance Brokerage & Risk Management | B15: 1 | C15: 9986344.6
... A34: Grand Total | B34: 124 | C34: 7.5418146e+08

Sheet sql

Sheet Pareto Analysis
A1: Vendor Rank | B1: Vendor Name | C1: Spend Amount | D1: Cumulative Spend | E1: Cumulative % | F1: Total Spend | H1: Summary
A2: 1 | B2: ='Enriched Data'!C2 -> Morgan Stanley | C2: ='Enriched Data'!G2 -> 1.7243952e+08 | D2: =C2 -> 1.7243952e+08 | E2: =D2/$F$2 -> 0.18431668 | F2: =SUM('Enriched Data'!G:G) -> 9.3556111e+08 | H2: Total Spend: | I2: =F2 -> 9.3556111e+08
A3: =A2+1 -> 2 | B3: {=INDEX('Enriched Data'!C:C,A3+1)} -> Tombras | C3: {=INDEX('Enriched Data'!G:G,A3+1)} -> 63836895 | D3: =D2+C3 -> 2.3627641e+08 | E3: =D3/$F$2 -> 0.25255049 | H3: 80% Threshold: | I3: =F2*0.8 -> 7.4844889e+08
A4: =A3+1 -> 3 | B4: {=INDEX('Enriched Data'!C:C,A4+1)} -> Blackhawk Transport Inc | C4: {=INDEX('Enriched Data'!G:G,A4+1)} -> 30035306 | D4: =D3+C4 -> 2.6631172e+08 | E4: =D4/$F$2 -> 0.28465454 | H4: Vendors for 80%: | I4: =COUNTIF(E2:E2225,"<=80%") -> 118
A5: =A4+1 -> 4 | B5: {=INDEX('Enriched Data'!C:C,A5+1)} -> Xn Financial -us | C5: {=INDEX('Enriched Data'!G:G,A5+1)} -> 27778217 | D5: =D4+C5 -> 2.9408994e+08 | E5: =D5/$F$2 -> 0.31434605 | H5: Total Vendors: | I5: 2224
A6: =A5+1 -> 5 | B6: {=INDEX('Enriched Data'!C:C,A6+1)} -> Ryder Transportation Services-CHIC | C6: {=INDEX('Enriched Data'!G:G,A6+1)} -> 23877181 | D6: =D5+C6 -> 3.1796712e+08 | E6: =D6/$F$2 -> 0.33986782 | H6: % of Vendors: | I6: =I4/I5 -> 0.053057554
A7: =A6+1 -> 6 | B7: {=INDEX('Enriched Data'!C:C,A7+1)} -> C R England Inc | C7: {=INDEX('Enriched Data'!G:G,A7+1)} -> 22269849 | D7: =D6+C7 -> 3.4023697e+08 | E7: =D7/$F$2 -> 0.36367156
A8: =A7+1 -> 7 | B8: {=INDEX('Enriched Data'!C:C,A8+1)} -> Schneider National Carriers, Inc. | C8: {=INDEX('Enriched Data'!G:G,A8+1)} -> 20887754 | D8: =D7+C8 -> 3.6112472e+08 | E8: =D8/$F$2 -> 0.385998 | H8: First vendor over 80%: | I8: {=MATCH(TRUE,E2:E2225>0.8,0)} -> 119
A9: =A8+1 -> 8 | B9: {=INDEX('Enriched Data'!C:C,A9+1)} -> Averitt Express | C9: {=INDEX('Enriched Data'!G:G,A9+1)} -> 19620030 | D9: =D8+C9 -> 3.8074475e+08 | E9: =D9/$F$2 -> 0.40696941 | H9: That vendor's name: | I9: {=INDEX(B:B,I8+1)} -> Almar Management LLC
A10: =A9+1 -> 9 | B10: {=INDEX('Enriched Data'!C:C,A10+1)} -> USA Truck LLC | C10: {=INDEX('Enriched Data'!G:G,A10+1)} -> 19166697 | D10: =D9+C10 -> 3.9991145e+08 | E10: =D10/$F$2 -> 0.42745625 | H10: Cumulative % at vendor 118: | I10: =E119 -> 0.79943967
A11: =A10+1 -> 10 | B11: {=INDEX('Enriched Data'!C:C,A11+1)} -> Concentrix Solutions Corporation | C11: {=INDEX('Enriched Data'!G:G,A11+1)} -> 15925508 | D11: =D10+C11 -> 4.1583696e+08 | E11: =D11/$F$2 -> 0.44447867 | H11: Cumulative % at vendor 119: | I11: =E120 -> 0.80057073
A12: =A11+1 -> 11 | B12: {=INDEX('Enriched Data'!C:C,A12+1)} -> NFI | C12: {=INDEX('Enriched Data'!G:G,A12+1)} -> 15576392 | D12: =D11+C12 -> 4.3141335e+08 | E12: =D12/$F$2 -> 0.46112792
A13: =A12+1 -> 12 | B13: {=INDEX('Enriched Data'!C:C,A13+1)} -> WEX Bank | C13: {=INDEX('Enriched Data'!G:G,A13+1)} -> 15479315 | D13: =D12+C13 -> 4.4689266e+08 | E13: =D13/$F$2 -> 0.47767341
A14: =A13+1 -> 13 | B14: {=INDEX('Enriched Data'!C:C,A14+1)} -> Fidelity 401K | C14: {=INDEX('Enriched Data'!G:G,A14+1)} -> 14258254 | D14: =D13+C14 -> 4.6115092e+08 | E14: =D14/$F$2 -> 0.49291373
A15: =A14+1 -> 14 | B15: {=INDEX('Enriched Data'!C:C,A15+1)} -> Marsh Usa Inc | C15: {=INDEX('Enriched Data'!G:G,A15+1)} -> 9986344.6 | D15: =D14+C15 -> 4.7113726e+08 | E15: =D15/$F$2 -> 0.50358791
A16: =A15+1 -> 15 | B16: {=INDEX('Enriched Data'!C:C,A16+1)} -> Cass Information Systems, Inc | C16: {=INDEX('Enriched Data'!G:G,A16+1)} -> 9468800.4 | D16: =D15+C16 -> 4.8060606e+08 | E16: =D16/$F$2 -> 0.51370889
A17: =A16+1 -> 16 | B17: {=INDEX('Enriched Data'!C:C,A17+1)} -> Liberty Mutual Insurance | C17: {=INDEX('Enriched Data'!G:G,A17+1)} -> 9425627.8 | D17: =D16+C17 -> 4.9003169e+08 | E17: =D17/$F$2 -> 0.52378373
A18: =A17+1 -> 17 | B18: {=INDEX('Enriched Data'!C:C,A18+1)} -> Salesforce.com | C18: {=INDEX('Enriched Data'!G:G,A18+1)} -> 9291128.2 | D18: =D17+C18 -> 4.9932282e+08 | E18: =D18/$F$2 -> 0.53371481
A19: =A18+1 -> 18 | B19: {=INDEX('Enriched Data'!C:C,A19+1)} -> Express Scripts, Inc | C19: {=INDEX('Enriched Data'!G:G,A19+1)} -> 8008657.3 | D19: =D18+C19 -> 5.0733148e+08 | E19: =D19/$F$2 -> 0.54227508
A20: =A19+1 -> 19 | B20: {=INDEX('Enriched Data'!C:C,A20+1)} -> Ernst & Young LLP | C20: {=INDEX('Enriched Data'!G:G,A20+1)} -> 7740476.9 | D20: =D19+C20 -> 5.1507195e+08 | E20: =D20/$F$2 -> 0.5505487
A21: =A20+1 -> 20 | B21: {=INDEX('Enriched Data'!C:C,A21+1)} -> J Hawk Inc | C21: {=INDEX('Enriched Data'!G:G,A21+1)} -> 7065487.9 | D21: =D20+C21 -> 5.2213744e+08 | E21: =D21/$F$2 -> 0.55810084
A22: =A21+1 -> 21 | B22: {=INDEX('Enriched Data'!C:C,A22+1)} -> Microsoft Licensing Gp | C22: {=INDEX('Enriched Data'!G:G,A22+1)} -> 7030985.7 | D22: =D21+C22 -> 5.2916843e+08 | E22: =D22/$F$2 -> 0.5656161
A23: =A22+1 -> 22 | B23: {=INDEX('Enriched Data'!C:C,A23+1)} -> Armstrong Transport Group Inc | C23: {=INDEX('Enriched Data'!G:G,A23+1)} -> 6489064 | D23: =D22+C23 -> 5.3565749e+08 | E23: =D23/$F$2 -> 0.57255211
... A2225: =A2224+1 -> 2224 | B2225: {=INDEX('Enriched Data'!C:C,A2225+1)} -> Kelly Dukes | C2225: {=INDEX('Enriched Data'!G:G,A2225+1)} -> 100 | D2225: =D2224+C2225 -> 9.3556111e+08 | E2225: =D2225/$F$2 -> 1
